annotamate/__init__.py
annotamate/__main__.py
annotamate/main.py
annotamate/assets/logo.ico
annotamate/assets/name_logo.png
annotamate-1.0.0.dist-info/licenses/LICENSE
annotamate-1.0.0.dist-info/METADATA
annotamate-1.0.0.dist-info/WHEEL
annotamate-1.0.0.dist-info/entry_points.txt
annotamate-1.0.0.dist-info/top_level.txt
annotamate-1.0.0.dist-info/RECORD
