Metadata-Version: 2.4
Name: annotamate
Version: 1.0.0
Summary: A Python package for image annotation
Home-page: https://github.com/rugvedjalit/Annotamate
Author: Rugved Jalit
Classifier: Programming Language :: Python :: 3
Classifier: License :: OSI Approved :: MIT License
Classifier: Operating System :: OS Independent
Requires-Python: >=3.6
License-File: LICENSE
Requires-Dist: customtkinter
Requires-Dist: pillow
Requires-Dist: tkfontawesome
Dynamic: author
Dynamic: classifier
Dynamic: description
Dynamic: description-content-type
Dynamic: home-page
Dynamic: license-file
Dynamic: requires-dist
Dynamic: requires-python
Dynamic: summary
